trellisplot/__init__.py
trellisplot/plot.py
trellisplot/utils.py
trellisplot-0.0.4.dist-info/METADATA
trellisplot-0.0.4.dist-info/WHEEL
trellisplot-0.0.4.dist-info/top_level.txt
trellisplot-0.0.4.dist-info/RECORD
