Metadata-Version: 2.1
Name: trellisplot
Version: 0.0.4
Summary: Trellis plot tool
Author: Ethan S. Lee
Author-email: <sukraelee@gmail.com>
Keywords: python,trellisplot
Classifier: Development Status :: 3 - Alpha
Classifier: Intended Audience :: Developers
Classifier: Programming Language :: Python :: 3
Classifier: Operating System :: Microsoft :: Windows
Requires-Dist: matplotlib
Requires-Dist: numpy
Requires-Dist: seaborn
Requires-Dist: pandas
Requires-Dist: scipy
